MLFastTrain/MLFastTrain.py
MLFastTrain/__init__.py
ml_fast_train-0.0.1.dist-info/LICENSE
ml_fast_train-0.0.1.dist-info/METADATA
ml_fast_train-0.0.1.dist-info/WHEEL
ml_fast_train-0.0.1.dist-info/top_level.txt
ml_fast_train-0.0.1.dist-info/RECORD
