Metadata-Version: 2.1
Name: ml-fast-train
Version: 0.0.1
Summary: Package to train basic models
Home-page: UNKNOWN
Author: rahmani ali
Author-email: rahmani53@gmail.com
License: UNKNOWN
Platform: UNKNOWN
Classifier: Programming Language :: Python :: 3
Classifier: License :: OSI Approved :: MIT License
Classifier: Operating System :: OS Independent
Requires-Python: >=3.6
